conda_join.py
conda_join-0.13.0.dist-info/LICENSE
conda_join-0.13.0.dist-info/METADATA
conda_join-0.13.0.dist-info/WHEEL
conda_join-0.13.0.dist-info/entry_points.txt
conda_join-0.13.0.dist-info/top_level.txt
conda_join-0.13.0.dist-info/RECORD
