Metadata-Version: 2.1
Name: conda-join
Version: 0.13.0
Summary: Unified Conda and Pip requirements management.
Author-email: Bas Nijholt <bas@nijho.lt>
Project-URL: Homepage, https://github.com/basnijholt/conda-join
Requires-Python: >=3.7
License-File: LICENSE
Requires-Dist: ruamel.yaml
Requires-Dist: typing-extensions ; python_version < "3.8"
Provides-Extra: test
Requires-Dist: pytest ; extra == 'test'
Requires-Dist: pre-commit ; extra == 'test'
Requires-Dist: coverage ; extra == 'test'
Requires-Dist: pytest-cov ; extra == 'test'
Requires-Dist: pytest-mock ; extra == 'test'
